proxyutils/__init__.py
proxyutils/converter.py
proxyutils/extension.py
proxyutils/extension_consts.py
proxyutils/extractor.py
proxyutils/proxy.py
proxyutils-0.1.0.dist-info/licenses/LICENSE
tests/__init__.py
tests/test_proxyparser.py
proxyutils-0.1.0.dist-info/METADATA
proxyutils-0.1.0.dist-info/WHEEL
proxyutils-0.1.0.dist-info/entry_points.txt
proxyutils-0.1.0.dist-info/top_level.txt
proxyutils-0.1.0.dist-info/RECORD
